 {
     "name": "route12",
     "route": {
         "start": {
             "x": "-29.64",
             "y": "1",
             "z": "2.2"
         },
         "finish": {
             "x": "",
             "y": "",
             "z": ""
         },
         "path": [{
             "movement": {
                 "x": "-29.68",
                 "y": "1",
                 "z": "-3.96",
                 "t": "2000"
             }
         },
         {
             "movement": {
               "x": "-25.31",
               "y": "1",
               "z": "-3.90",
               "t": "2000"
             }
         },
         {
             "movement": {
               "x": "-24.61",
               "y": "1",
               "z": "11.68",
               "t": "2000"
             }
         }, {
             "movement": {
               "x": "-25.05",
               "y": "1",
               "z": "-4.20",
               "t": "2000"
             }
         }, {
             "movement": {
               "x": "-29.71",
               "y": "1",
               "z": "-3.9",
               "t": "2000"
             }
         },{
             "movement": {
               "x": "-29.71",
               "y": "1",
               "z": "-3.9",
               "t": "2000"
             }
         },{
             "movement": {
               "x": "-29.51",
               "y": "1",
               "z": "-3.9",
               "t": "2000"
             }
         },{
             "movement": {
               "x": "-29.97",
               "y": "1",
               "z": "2.83",
               "t": "2000"
             }
         },{
             "movement": {
               "x": "-29.97",
               "y": "4",
               "z": "2.83",
               "t": "2000"
             }
         }, {
             "movement": {
               "x": "-29.88",
               "y": "4",
               "z": "11.50",
               "t": "2000"
             }
         },{
             "movement": {
               "x": "-26.70",
               "y": "4",
               "z": "12.00",
               "t": "2000"
             }
         },{
             "movement": {
               "x": "-25.77",
               "y": "4",
               "z": "19.54",
               "t": "2000"
             }
         },{
             "movement": {
               "x": "-25.77",
               "y": "4",
               "z": "19.54",
               "t": "2000"
             }
         },{
             "movement": {
               "x": "-25.77",
               "y": "1",
               "z": "19.54",
               "t": "2000"
             }
         },{
             "movement": {
               "x": "-29.41",
               "y": "1",
               "z": "15.17",
               "t": "2000"
             }
         },{
             "movement": {
               "x": "-29.64",
               "y": "1",
               "z": "9.14",
               "t": "2000"
             }
         }]
     }
 }
