 {
     "name": "route12",
     "route": {
         "start": {
             "x": "",
             "y": "",
             "z": ""
         },
         "finish": {
             "x": "",
             "y": "",
             "z": ""
         },
         "path": [{
             "movement": {
                 "x": "",
                 "y": "",
                 "z": ""
             }
         }, {
             "movement": {
                 "x": "",
                 "y": "",
                 "z": ""
             }
         }, {
             "movement": {
                 "x": "",
                 "y": "",
                 "z": ""
             }
         }]
     }
 }
